charmer/__init__.py
charmer/__main__.py
charmer/cmd.py
charmer/constants.py
charmer/initializer.py
charmer/inputs.py
charmer/questionnaire.py
charmer/runner.py
charmer/setup_handler.py
charmer/templates.py
charmer-0.1.0.dist-info/METADATA
charmer-0.1.0.dist-info/RECORD
charmer-0.1.0.dist-info/WHEEL
charmer-0.1.0.dist-info/entry_points.txt
charmer-0.1.0.dist-info/top_level.txt
