Metadata-Version: 2.1
Name: charmer
Version: 0.1.0
Summary: A commandline interface for creating project structures
Home-page: UNKNOWN
Author: Ramon Hagenaars
Author-email: UNKNOWN
License: UNKNOWN
Platform: UNKNOWN
